realpython_pypi_tut/__init__.py
realpython_pypi_tut/dogge.py
realpython_pypi_tut/not_something.pdf
realpython_pypi_tut/something.txt
rp_pypi_tut_flit-0.1.0.dist-info/WHEEL
rp_pypi_tut_flit-0.1.0.dist-info/METADATA
rp_pypi_tut_flit-0.1.0.dist-info/RECORD
