Metadata-Version: 2.1
Name: rp_pypi_tut_flit
Version: 0.1.0
Summary: Docstring here.
Home-page: UNKNOWN
License: UNKNOWN
Author: iljaz
Author-email: iljaz@iljaz.com
Classifier: License :: OSI Approved :: MIT License
